text_util/__init__.py
text_util/cli.py
text_util-0.1.1.dist-info/entry_points.txt
text_util-0.1.1.dist-info/WHEEL
text_util-0.1.1.dist-info/METADATA
text_util-0.1.1.dist-info/RECORD
